LICENSE
MANIFEST.in
README.md
setup.cfg
setup.py
fairules/README.txt
fairules/__init__.py
fairules/_corels.cpp
fairules/corels.py
fairules/utils.py
fairules.egg-info/PKG-INFO
fairules.egg-info/SOURCES.txt
fairules.egg-info/dependency_links.txt
fairules.egg-info/requires.txt
fairules.egg-info/top_level.txt
fairules/src/utils.cpp
fairules/src/utils.hh
fairules/src/corels/src/alloc.hh
fairules/src/corels/src/cache.cpp
fairules/src/corels/src/cache.hh
fairules/src/corels/src/corels.cpp
fairules/src/corels/src/pmap.cpp
fairules/src/corels/src/pmap.hh
fairules/src/corels/src/queue.hh
fairules/src/corels/src/rule.hh
fairules/src/corels/src/rulelib.cpp
fairules/src/corels/src/run.cpp
fairules/src/corels/src/run.hh
fairules/src/corels/src/utils.cpp
fairules/src/corels/src/utils.hh