Metadata-Version: 1.2
Name: fairules
Version: 1.6
Summary: FairCORELS, a modified version of CORELS to build fair and interpretable models
Home-page: https://github.com/aivodji/fairules
Author: Elaine Angelino, Nicholas Larus-Stone, Hongyu Yang, Cythnia Rudin, Vassilios Kaxiras, Margo Seltzer, Ulrich Aïvodji, Julien Ferry, Sébastien Gambs, Marie-José Huguet, Mohamed Siala
Author-email: a.u.matchi@gmail.com
License: GNU General Public License v3 (GPLv3)
Download-URL: https://github.com/aivodji/fairules/archive/v1.6.tar.gz
Platform: UNKNOWN
Classifier: Programming Language :: C++
Classifier: License :: OSI Approved :: GNU General Public License v3 (GPLv3)
Classifier: Operating System :: OS Independent
Requires-Python: >=2.7
